{
  "collectionName": "components_chunks_chunk1s",
  "info": {
    "displayName": "chunk1",
    "description": ""
  },
  "options": {},
  "attributes": {
    "label": {
      "type": "string"
    },
    "Description": {
      "type": "text"
    },
    "content": {
      "displayName": "content",
      "type": "component",
      "repeatable": true,
      "component": "chunks.content"
    },
    "visible": {
      "type": "boolean"
    },
    "section": {
      "type": "enumeration",
      "enum": [
        "AddedSect__",
        "Section-1",
        "Section-2",
        "Section-3",
        "Section-4",
        "Section-5",
        "Section-6",
        "Section-7",
        "Section-8",
        "Section-9",
        "Section-10"
      ]
    },
    "Image": {
      "type": "media",
      "multiple": false,
      "required": false,
      "allowedTypes": [
        "images",
        "files",
        "videos",
        "audios"
      ]
    }
  }
}
